jsonrpcdjango/__init__.py
jsonrpcdjango/loader.py
jsonrpcdjango/templates/jsonrpc/introspection.html
jsonrpcdjango/templates/jsonrpc/introspection.tracwiki
damn_simple_jsonrpc_server_django-0.5.dist-info/METADATA
damn_simple_jsonrpc_server_django-0.5.dist-info/WHEEL
damn_simple_jsonrpc_server_django-0.5.dist-info/top_level.txt
damn_simple_jsonrpc_server_django-0.5.dist-info/RECORD
